quoine/__init__.py
quoine/quoine.py
quoine-0.0.1.dist-info/DESCRIPTION.rst
quoine-0.0.1.dist-info/METADATA
quoine-0.0.1.dist-info/RECORD
quoine-0.0.1.dist-info/WHEEL
quoine-0.0.1.dist-info/metadata.json
quoine-0.0.1.dist-info/top_level.txt
